{"Names":{"Category":"name","Choices":["Aldric","Aldo","Amosen","Andrel","Arden","Arlyn","Arquo","Arvus","Ashlyn","Branon","Brace","Brance","Brena","Bricks","Candra","Carissa","Carro","Casslyn","Cavelle","Clave","Corille","Cross","Crowl","Cyrene","Daphnia","Drav","Edlun","Emeline","Grine","Helles","Hix","Holtz","Kamelin","Kelyr","Kobb","Kristov","Laudius","Lauria","Lenia","Lizete","Lorette","Lucella","Lynthia","Mara","Milos","Morlan","Myre","Narcus","Naria","Noggs","Odrienne","Orlan","Phin","Polonia","Quess","Remira","Ring","Roethe","Sesereth","Sethla","Skannon","Stavrul","Stev","Syra","Talitha","Tesslyn","Thena","Timoth","Tocker","Una","Vaurin","Veleris","Veretta","Vestine","Vey","Volette","Vond","Weaver","Wester","Zamira"]},"Aliases":{"Category":"Alias","Choices":["Bell","Birch","Bricks","Bug","Chime","Coil","Cricket","Cross","Crow","Echo","Flint","Frog","Frost","Grip","Gunner","Hammer","Hook","Junker","Mist","Moon","Nail","Needle","Ogre","Pool","Ring","Ruby","Silver","Skinner","Song","Spur","Tackle","Thisle","Thorn","Tick-Tock","Twelves","Vixen","Whip","Wicker"]},"FamilyNames":{"Category":"family name","Choices":["Ankhayat","Arran","Athanoch","Basran","Boden","Booker","Bowman","Breakiron","Brogan","Clelland","Clermont","Coleburn","Comber","Daeva","Dalmore","Danfield","Dunvil","Farros","Grine","Haig","Helker","Helles","Helyers","Jayan","Jeduin","Kardera","Karstas","Keel","Kessarin","Kinclaith","Lomond","Maroden","Michter","Morriston","Penderyn","Prichard","Rowan","Sevoy","Skekallan","Skora","Slane","Strangford","Strathmill","Templeton","Tyrconnel","Vale","Walund","Welker"]},"Heritages":{"Category":"heritage","Choices":["Akorosi","Akorosi","Akorosi","Akorosi","Akorosi","Akorosi","Skovlander","Skovlander","Iruvian","Dagger Islander","Severosi","Tycherosi"]},"Professions":{"Category":"profession","Choices":["baker","baker","baker","baker","baker","barber","barber","barber","barber","barber","blacksmith","blacksmith","blacksmith","blacksmith","blacksmith","brewer","brewer","brewer","brewer","brewer","butcher","butcher","butcher","butcher","butcher","carpenter","carpenter","carpenter","carpenter","carpenter","cartwright","cartwright","cartwright","cartwright","cartwright","chandler","chandler","chandler","chandler","chandler","clerk","clerk","clerk","clerk","clerk","cobbler","cobbler","cobbler","cobbler","cobbler","cooper","cooper","cooper","cooper","cooper","cultivator","cultivator","cultivator","cultivator","cultivator","driver","driver","driver","driver","driver","dyer","dyer","dyer","dyer","dyer","embroiderer","embroiderer","embroiderer","embroiderer","embroiderer","fishmonger","fishmonger","fishmonger","fishmonger","fishmonger","gondolier","gondolier","gondolier","gondolier","gondolier","guard","guard","guard","guard","guard","leatherworker","leatherworker","leatherworker","leatherworker","leatherworker","mason","mason","mason","mason","mason","merchant","merchant","merchant","merchant","merchant","roofer","roofer","roofer","roofer","roofer","ropemaker","ropemaker","ropemaker","ropemaker","ropemaker","rug maker","rug maker","rug maker","rug maker","rug maker","servant","servant","servant","servant","servant","shipwright","shipwright","shipwright","shipwright","shipwright","criminal","criminal","criminal","criminal","criminal","tailor","tailor","tailor","tailor","tailor","tanner","tanner","tanner","tanner","tanner","tinkerer","tinkerer","tinkerer","tinkerer","tinkerer","vendor","vendor","vendor","vendor","vendor","weaver","weaver","weaver","weaver","weaver","woodworker","woodworker","woodworker","woodworker","woodworker","goat heard","goat heard","goat heard","goat heard","goat heard","messenger","messenger","messenger","messenger","messenger","sailor","sailor","sailor","sailor","sailor","advocate","architect","artist","author","bailiff","apiarist","banker","bounty hunter","clockmaker","courtesan","furrier","glass blower","diplomat","jailer","jeweler","leech","locksmith","magistrate","musician","physicker","plumber","printer","scholar","scribe","sparkwright","tax collector","treasurer","whisper","composer","steward","captain","spirit warden","journalist","explorer","rail jack","soldier"]},"Looks":{"Category":"look","Choices":["large","lovely","weathered","chiseled","handsome","slim","dark","fair","stout","delicate","scarred","bony","worn","rough","plump","wiry","striking","short","tall","sexy","wild","elegant","stooped","cute","plain","old","young","stylish","strange","disfigured","maimed","glasses","monocle","prosthetic","crippled","long hair","beard","wig","shorn","bald","tattoed"]},"Styles":{"Category":"style","Choices":["tricorn hat","long coat","hood & veil","short cloak","knit cap","slim jacket","hooded coat","tall boots","work boots","mask & robe","suit & vest","collared shirt","suspenders","rough tunic","skirt & blouse","wide belt","fitted dress","heavy cloak","thick greatcoat","soft boots","loose silks","sharp trousers","waxed coat","long scarf","leathers","eelskin bodysuit","hide & furs","uniform","tatters","fitted leggings","apron","heavy gloves","face mask","tool belt","crutches","cane","wheelchair"]},"Goals":{"Category":"goal","Choices":["wealth","power","authority","prestige","fame","control","knowledge","pleasure","revenge","freedom","achievement","happiness","infamy","fear","respect","love","change","chaos","destruction","justice","cooperation"]},"Methods":{"Category":"method","Choices":["violence","threats","negotiation","study","manipulation","strategy","theft","arcane","commerce","hardwork","law","politics","sabotage","subterfuge","alchemy","blackmail","teamwork","espionage","chaos"]},"Traits":{"Category":"trait","Choices":["charming","cold","cavalier","brash","suspicious","obsessive","shrewd","quiet","moody","fierce","careless","secretive","ruthless","calculating","defiant","gracious","insightful","dishonest","patient","vicious","sophisticated","paranoid","enthusiastic","elitist","savage","cooperative","arrogant","confident","vain","daring","volatile","candid","subtle","melancholy","enigmatic","calm"]},"Interests":{"Category":"interest","Choices":["fine whiskey","fine wine","fine beer","fine food","fine restaurants","fine clothes","fine jewelry","fine furs","fine arts","opera","theater","painting","drawing","sculpture","history","legends","architecture","furnishings","poetry","novels","writing","pit fighting","duels","forgotten gods","Church of Ecstasy","Path of Echoes","Weeping Lady","charity","antiques","artifacts","curios","horses","riding","gadgets","new technology","weapons collector","music","music instruments","dance","hunting","shooting","cooking","gardening","gambling","cards","dice","natural philosophy","drugs","essences","tobacco","lovers","romance","trysts","parties","social events","exploration","adventure","pets","crafts","ships","boating","politics","journalism","arcane books","arcane rituals","spectrology","electroplasm","alchemy","medicine","demon lore","pre cataclysm legends"]},"Quirks":{"Category":"quirk","Choices":["superstitious","believes in signs","believes in magic numbers","devoted to family","married into important family","holds their position to spy for faction","reclusive","interacts via messengers","massive debt","blind to flaws in friends","hollowed, then restored","immune to ghosts","chronic illness that requires care","controlled by spirit","serves demon's agenda","proud of heritage","concerned with appearances","substance abuse, often impaired","used blackmail to hold position","relies on council to decide","involved with war crimes from Unity War","leads double life","black sheep from family, faction","in prison, house arrest","well travelled and connected","revolutionary, against Imperium","inherited position","celebrity","scandalous reputation","surrounded by sycophants","spotless reputation, highly regarded","bigoted","visionary, radical views","cursed, harassed by spirit or demon","intense phobia","extensive education","keeps notes, ledgers","blindly faithful to ideal","deeply traditional, opposed to new ideas","fraud, fabricated life"]}}